a3exception/__init__.py
a3exception/dynamic_error_factory.py
a3exception/errors.py
a3exception-0.3.0.dist-info/LICENSE
a3exception-0.3.0.dist-info/METADATA
a3exception-0.3.0.dist-info/WHEEL
a3exception-0.3.0.dist-info/top_level.txt
a3exception-0.3.0.dist-info/RECORD
